pycee/__init__.py
pycee/answers.py
pycee/errors.py
pycee/inspection.py
pycee/sym_table.py
pycee/utils.py
pycee2-0.1.data/scripts/usage.py
pycee2-0.1.dist-info/LICENSE
pycee2-0.1.dist-info/METADATA
pycee2-0.1.dist-info/WHEEL
pycee2-0.1.dist-info/entry_points.txt
pycee2-0.1.dist-info/top_level.txt
pycee2-0.1.dist-info/RECORD
