Metadata-Version: 2.1
Name: pycee2
Version: 0.1
Summary: Enhanced error messages from Stackoverflow
Home-page: https://github.com/marcelofa/pycee2
Author: Marcelo Freitas
Author-email: jmfda00@gmail.com
Maintainer: Leonardo Furtado
Maintainer-email: srleonardofurtado@gmail.com
License: UNKNOWN
Platform: UNKNOWN
Classifier: Programming Language :: Python
Classifier: Programming Language :: Python :: 3
Classifier: Programming Language :: Python :: 3.7
Requires-Python: >=3.7.0
Requires-Dist: requests
Requires-Dist: python-slugify
Requires-Dist: filecache
Requires-Dist: googlesearch-python
Requires-Dist: html2text
Requires-Dist: consolemd
